morcecodetranslator/__init__.py
morcecodetranslator/morce.py
morcecodetranslator-1.0.2.dist-info/LICENSE.md
morcecodetranslator-1.0.2.dist-info/METADATA
morcecodetranslator-1.0.2.dist-info/WHEEL
morcecodetranslator-1.0.2.dist-info/top_level.txt
morcecodetranslator-1.0.2.dist-info/RECORD
