Metadata-Version: 2.1
Name: morcecodetranslator
Version: 1.0.2
Summary: Convert text to Morce Code
Home-page: https://github.com/gugupy/morcecodetranslator
Author: Gughanathan M
Author-email: gugu.ap900@gmail.com
License: MIT
Keywords: Morce Code
Classifier: Programming Language :: Python :: 3
Classifier: Operating System :: OS Independent
Requires-Python: >=3.6
License-File: LICENSE.md
